README.md
setup.py
agrafena/__about__.py
agrafena/__init__.py
agrafena.egg-info/PKG-INFO
agrafena.egg-info/SOURCES.txt
agrafena.egg-info/dependency_links.txt
agrafena.egg-info/requires.txt
agrafena.egg-info/top_level.txt